MANIFEST.in
README.md
pyproject.toml
src/gg_langchain.egg-info/PKG-INFO
src/gg_langchain.egg-info/SOURCES.txt
src/gg_langchain.egg-info/dependency_links.txt
src/gg_langchain.egg-info/requires.txt
src/gg_langchain.egg-info/top_level.txt
src/langchain_gridgain/__init__.py
src/langchain_gridgain/chat_message_histories.py
src/langchain_gridgain/document_loaders.py
src/langchain_gridgain/llm_cache.py
src/langchain_gridgain/storage.py
src/langchain_gridgain/vectorstores.py
src/langchain_gridgain.egg-info/PKG-INFO
src/langchain_gridgain.egg-info/SOURCES.txt
src/langchain_gridgain.egg-info/dependency_links.txt
src/langchain_gridgain.egg-info/requires.txt
src/langchain_gridgain.egg-info/top_level.txt
src/langchain_gridgain/__pycache__/__init__.cpython-311.pyc
src/langchain_gridgain/__pycache__/chat_message_histories.cpython-311.pyc
src/langchain_gridgain/__pycache__/document_loaders.cpython-311.pyc
src/langchain_gridgain/__pycache__/llm_cache.cpython-311.pyc
src/langchain_gridgain/__pycache__/storage.cpython-311.pyc
src/langchain_gridgain/__pycache__/vectorstores.cpython-311.pyc
tests/README.md
tests/__init__.py
tests/__pycache__/__init__.cpython-310.pyc
tests/__pycache__/__init__.cpython-311.pyc
tests/__pycache__/__init__.cpython-312.pyc
tests/integration/__init__.py
tests/integration/test_chat_message_histories.py
tests/integration/test_document_loaders.py
tests/integration/test_llm_cache.py
tests/integration/test_semantic_llm_cache.py
tests/integration/test_storage.py
tests/integration/test_vectorstores.py
tests/integration/__pycache__/__init__.cpython-310.pyc
tests/integration/__pycache__/__init__.cpython-311.pyc
tests/integration/__pycache__/test_chat_message_histories.cpython-310-pytest-8.3.4.pyc
tests/integration/__pycache__/test_chat_message_histories.cpython-311-pytest-8.3.4.pyc
tests/integration/__pycache__/test_document_loaders.cpython-310-pytest-8.3.4.pyc
tests/integration/__pycache__/test_document_loaders.cpython-311-pytest-8.3.4.pyc
tests/integration/__pycache__/test_llm_cache.cpython-310-pytest-8.3.4.pyc
tests/integration/__pycache__/test_llm_cache.cpython-311-pytest-8.3.4.pyc
tests/integration/__pycache__/test_semantic_llm_cache.cpython-310-pytest-8.3.4.pyc
tests/integration/__pycache__/test_semantic_llm_cache.cpython-311-pytest-8.3.4.pyc
tests/integration/__pycache__/test_storage.cpython-310-pytest-8.3.4.pyc
