Metadata-Version: 2.4
Name: langchain-gridgain
Version: 1.0.2
Summary: This package makes it possible to use Gridgain as a Vector Store, Document Loader, LLM Cache, Key Value Store, Chat Memory within langchain 
Author-email: Manini Puranik <manini.puranik@gridgain.com>, Aditi Sharma <aditi.sharma@gridgain.com>
Requires-Python: >=3.10
Requires-Dist: langchain==0.3.21
Requires-Dist: langchain-community~=0.3.20
Requires-Dist: pyignite==0.6.1
Requires-Dist: pygridgain==1.5.0
Provides-Extra: test
Requires-Dist: pytest; extra == "test"
Requires-Dist: pytest-asyncio; extra == "test"
Provides-Extra: coverage
Requires-Dist: pytest-cov; extra == "coverage"
